sitt/__about__.py
sitt/__init__.py
sitt/__main__.py
sitt/base.py
sitt/cl.py
sitt/core.py
sitt/loaders.py
sitt/py.typed
sitt/sim_runner.py
sitt/utils.py
sitt/modules/__init__.py
sitt/modules/output/__init__.py
sitt/modules/output/json_output.py
sitt/modules/preparation/__init__.py
sitt/modules/preparation/calculate_roads_and_hubs.py
sitt/modules/preparation/conditional_module.py
sitt/modules/preparation/create_routes.py
sitt/modules/preparation/debug_display_roads_and_hubs.py
sitt/modules/preparation/dummy.py
sitt/modules/preparation/geotiff_height_for_roads_and_hubs.py
sitt/modules/preparation/graph_load.py
sitt/modules/preparation/graph_save.py
sitt/modules/preparation/load_data_from_netcdf.py
sitt/modules/preparation/post_clean_raw_data.py
sitt/modules/preparation/psql_read_roads_and_hubs.py
sitt/modules/preparation/psql_save_roads_and_hubs.py
sitt/modules/simulation_step/__init__.py
sitt/modules/simulation_step/dummy_fixed_speed.py
sitt/modules/simulation_step/simple.py
sitt/modules/simulation_step/simple_with_environment.py
sitt-0.0.2.dist-info/METADATA
sitt-0.0.2.dist-info/WHEEL
sitt-0.0.2.dist-info/licenses/LICENSE.txt
sitt-0.0.2.dist-info/RECORD
