Metadata-Version: 2.1
Name: sitt
Version: 0.0.2
Summary: Si.T.T. (Simulation of Traffic and Transport) is an agent-based simulation for pre-industrial trade routes.
Project-URL: Documentation, https://github.com/Simulation-of-Traffic-and-Transport/SiTT#readme
Project-URL: Issues, https://codeberg.org/SiTT/SiTT/issues
Project-URL: Source, https://codeberg.org/SiTT/SiTT
Author-email: Maximilian Kalus <info@auxnet.de>
License-File: LICENSE.txt
Keywords: ancient,history,simulation,trade,university
Classifier: Development Status :: 2 - Pre-Alpha
Classifier: Intended Audience :: Education
Classifier: Intended Audience :: Science/Research
Classifier: License :: OSI Approved :: MIT License
Classifier: Operating System :: OS Independent
Classifier: Programming Language :: Python
Classifier: Programming Language :: Python :: 3 :: Only
Classifier: Programming Language :: Python :: 3.10
Classifier: Programming Language :: Python :: 3.11
Classifier: Programming Language :: Python :: Implementation :: CPython
Classifier: Programming Language :: Python :: Implementation :: PyPy
Classifier: Topic :: Scientific/Engineering
Classifier: Typing :: Typed
Requires-Python: >=3.10
Requires-Dist: cdsapi>=0.5.1
Requires-Dist: geopandas>=0.12.1
Requires-Dist: matplotlib>=3.6.2
Requires-Dist: nanoid~=2.0.0
Requires-Dist: netcdf4>=1.6.0
Requires-Dist: networkx~=2.8.8
Requires-Dist: numpy>=1.23.5
Requires-Dist: pandas>=1.5.1
Requires-Dist: pyproj>=3.4.0
Requires-Dist: pyyaml>=6.0
Requires-Dist: rasterio==1.3a3
Requires-Dist: rioxarray>=0.12.2
Requires-Dist: shapely>=1.8.5
Requires-Dist: sqlalchemy>=1.4.44
